bssunfold/__init__.py
bssunfold/constants.py
bssunfold/detector.py
bssunfold-0.1.3.dist-info/METADATA
bssunfold-0.1.3.dist-info/WHEEL
bssunfold-0.1.3.dist-info/entry_points.txt
bssunfold-0.1.3.dist-info/licenses/LICENSE
bssunfold-0.1.3.dist-info/RECORD
