Metadata-Version: 2.4
Name: bssunfold
Version: 0.1.3
Summary: Python package for neutron spectrum unfolding from measurements obtained with Bonner Sphere Spectrometer (BSS)
Project-URL: Homepage, https://github.com/Radiationsafety/bssunfold
Project-URL: Issues, https://github.com/Radiationsafety/bssunfold/issues
Project-URL: Repository, https://github.com/Radiationsafety/bssunfold.git
Project-URL: Changelog, https://github.com/Radiationsafety/bssunfold/blob/main/CHANGELOG.md
Author-email: Konstantin Chizhov <kchizhov@jinr.ru>, Alexei Chizhov <chizhov@jinr.ru>, Dmitry Borschev <bds.22@uni-dubna.ru>, Maria Akimochkina <a.m.a.mos@yandex.ru>
Maintainer-email: Konstantin Chizhov <kchizhov@jinr.ru>
License-Expression: GPL-3.0-only
License-File: LICENSE
Keywords: BSS,Bonner sphere spectrometer,ill-posed task,inverse problem,unfolding
Classifier: Development Status :: 4 - Beta
Classifier: Operating System :: OS Independent
Classifier: Programming Language :: Python :: 3
Classifier: Programming Language :: Python :: 3.11
Classifier: Programming Language :: Python :: 3.12
Classifier: Programming Language :: Python :: 3.13
Classifier: Topic :: Scientific/Engineering :: Mathematics
Classifier: Topic :: Scientific/Engineering :: Physics
Classifier: Topic :: Software Development :: Libraries :: Python Modules
Requires-Python: >=3.11
Requires-Dist: cvxpy[cvxopt,ecos]>=1.1
Requires-Dist: matplotlib>=3.10.8
Requires-Dist: numpy>=2.0.2
Requires-Dist: pandas>=2.2.3
Requires-Dist: pyzmq>=27.1.0
Requires-Dist: scipy>=1.16.3
